odoo/addons/sale_order_blanket_order_sale_margin/README.rst
odoo/addons/sale_order_blanket_order_sale_margin/__init__.py
odoo/addons/sale_order_blanket_order_sale_margin/__manifest__.py
odoo/addons/sale_order_blanket_order_sale_margin/i18n/it.po
odoo/addons/sale_order_blanket_order_sale_margin/i18n/sale_order_blanket_order_sale_margin.pot
odoo/addons/sale_order_blanket_order_sale_margin/models/__init__.py
odoo/addons/sale_order_blanket_order_sale_margin/models/sale_order_line.py
odoo/addons/sale_order_blanket_order_sale_margin/readme/CONTRIBUTORS.md
odoo/addons/sale_order_blanket_order_sale_margin/readme/CREDITS.md
odoo/addons/sale_order_blanket_order_sale_margin/readme/DESCRIPTION.md
odoo/addons/sale_order_blanket_order_sale_margin/static/description/icon.png
odoo/addons/sale_order_blanket_order_sale_margin/static/description/index.html
odoo/addons/sale_order_blanket_order_sale_margin/tests/__init__.py
odoo/addons/sale_order_blanket_order_sale_margin/tests/test_sale_call_off_order.py
odoo_addon_sale_order_blanket_order_sale_margin-16.0.1.0.0.4.dist-info/METADATA
odoo_addon_sale_order_blanket_order_sale_margin-16.0.1.0.0.4.dist-info/WHEEL
odoo_addon_sale_order_blanket_order_sale_margin-16.0.1.0.0.4.dist-info/top_level.txt
odoo_addon_sale_order_blanket_order_sale_margin-16.0.1.0.0.4.dist-info/RECORD
