Metadata-Version: 2.1
Name: odoo-addon-sale_order_blanket_order_sale_margin
Version: 16.0.1.0.0.4
Summary: Ensure sale margins are properly set on call off order lines
Home-page: https://github.com/OCA/sale-blanket
Author: ACSONE SA/NV,Odoo Community Association (OCA)
Author-email: support@odoo-community.org
License: AGPL-3
Classifier: Programming Language :: Python
Classifier: Framework :: Odoo
Classifier: Framework :: Odoo :: 16.0
Classifier: License :: OSI Approved :: GNU Affero General Public License v3
Requires-Python: >=3.10
Requires-Dist: odoo-addon-sale-order-blanket-order<16.1dev,>=16.0dev
Requires-Dist: odoo<16.1dev,>=16.0a
